chaosk8s/__init__.py
chaosk8s/actions.py
chaosk8s/chaosmesh/__init__.py
chaosk8s/chaosmesh/network/__init__.py
chaosk8s/chaosmesh/network/actions.py
chaosk8s/chaosmesh/network/probes.py
chaosk8s/chaosmesh/stress/__init__.py
chaosk8s/chaosmesh/stress/actions.py
chaosk8s/chaosmesh/stress/probes.py
chaosk8s/crd/__init__.py
chaosk8s/crd/actions.py
chaosk8s/crd/probes.py
chaosk8s/daemonset/__init__.py
chaosk8s/daemonset/actions.py
chaosk8s/daemonset/probes.py
chaosk8s/deployment/__init__.py
chaosk8s/deployment/actions.py
chaosk8s/deployment/probes.py
chaosk8s/event/__init__.py
chaosk8s/event/probes.py
chaosk8s/namespace/__init__.py
chaosk8s/namespace/actions.py
chaosk8s/namespace/probes.py
chaosk8s/networking/__init__.py
chaosk8s/networking/actions.py
chaosk8s/networking/probes.py
chaosk8s/node/__init__.py
chaosk8s/node/actions.py
chaosk8s/node/probes.py
chaosk8s/pod/__init__.py
chaosk8s/pod/actions.py
chaosk8s/pod/probes.py
chaosk8s/probes.py
chaosk8s/replicaset/__init__.py
chaosk8s/replicaset/actions.py
chaosk8s/secret/__init__.py
chaosk8s/secret/actions.py
chaosk8s/secret/probes.py
chaosk8s/service/__init__.py
chaosk8s/service/actions.py
chaosk8s/service/probes.py
chaosk8s/statefulset/__init__.py
chaosk8s/statefulset/actions.py
chaosk8s/statefulset/probes.py
chaostoolkit_kubernetes-0.38.2.dist-info/METADATA
chaostoolkit_kubernetes-0.38.2.dist-info/WHEEL
chaostoolkit_kubernetes-0.38.2.dist-info/licenses/LICENSE
chaostoolkit_kubernetes-0.38.2.dist-info/RECORD
