Metadata-Version: 2.1
Name: chaostoolkit-kubernetes
Version: 0.38.2
Summary: Chaos Toolkit Extension for Kubernetes
Author-Email: Chaos Toolkit <contact@chaostoolkit.org>
License: Apache-2.0
Classifier: Development Status :: 4 - Beta
Classifier: Intended Audience :: Developers
Classifier: License :: Freely Distributable
Classifier: License :: OSI Approved :: Apache Software License
Classifier: Operating System :: OS Independent
Classifier: Programming Language :: Python
Classifier: Programming Language :: Python :: 3
Classifier: Programming Language :: Python :: 3.8
Classifier: Programming Language :: Python :: 3.9
Classifier: Programming Language :: Python :: 3.10
Classifier: Programming Language :: Python :: 3.11
Classifier: Programming Language :: Python :: 3.12
Classifier: Programming Language :: Python :: Implementation
Classifier: Programming Language :: Python :: Implementation :: CPython
Project-URL: Documentation, https://chaostoolkit.org
Project-URL: Repository, https://github.com/chaostoolkit/chaostoolkit-kubernetes
Project-URL: Changelog, https://github.com/chaostoolkit/chaostoolkit-kubernetes/blob/master/CHANGELOG.md
Requires-Python: >=3.8
Requires-Dist: chaostoolkit-lib>=1.42.1
Requires-Dist: kubernetes>=29.0.0
Requires-Dist: dateparser>=1.2.0
Requires-Dist: pyyaml>=6.0.1
